LICENSE.txt
MANIFEST.in
README.md
setup.py
asr_phoneme_assessment.egg-info/PKG-INFO
asr_phoneme_assessment.egg-info/SOURCES.txt
asr_phoneme_assessment.egg-info/dependency_links.txt
asr_phoneme_assessment.egg-info/requires.txt
asr_phoneme_assessment.egg-info/top_level.txt
utils/__init__.py
utils/data_input.py
utils/generalfunc.py
utils/noise_sidefunc.py
utils/phone_error_rate.py
utils/standardizer.py
utils/timit_load.py