Metadata-Version: 1.1
Name: asr-phoneme-assessment
Version: 0.0.1
Summary: Provides Phoneme Error Rate & Visualisation Assessment
Home-page: UNKNOWN
Author: Jonathan Lim
Author-email: Jonathanlimws@gmail.com
License: MIT
Keywords: ASR
Platform: UNKNOWN
Classifier: Development Status :: 5 - Production/Stable
Classifier: Intended Audience :: Science/Research
Classifier: Operating System :: MacOS
Classifier: License :: OSI Approved :: MIT License
Classifier: Programming Language :: Python :: 3
